sqlitekvstore.py
sqlitekvstore-0.4.0.dist-info/METADATA
sqlitekvstore-0.4.0.dist-info/WHEEL
sqlitekvstore-0.4.0.dist-info/licenses/LICENSE
sqlitekvstore-0.4.0.dist-info/RECORD
