Metadata-Version: 2.4
Name: sqlitekvstore
Version: 0.4.0
Summary: Simple key-value store backed by sqlite
Project-URL: Home, https://github.com/RhetTbull/sqlitekvstore
Author-email: Rhet Turnbull <rturnbull+git@gmail.com>
License: MIT License
License-File: LICENSE
Classifier: License :: OSI Approved :: MIT License
Classifier: Programming Language :: Python :: 3
Classifier: Programming Language :: Python :: 3.10
Classifier: Programming Language :: Python :: 3.11
Classifier: Programming Language :: Python :: 3.12
Classifier: Programming Language :: Python :: 3.13
Classifier: Programming Language :: Python :: 3.14
Requires-Python: >=3.9
